[
  {
    "estadio": "Norte",
    "banda": "Prueba 1",
    "fecha": "13/02/2025 12:45"
  },
  {
    "estadio": "Norte",
    "banda": "Prueba 2",
    "fecha": "13/02/2025 12:50"
  },
  {
    "estadio": "Norte",
    "banda": "Prueba 3",
    "fecha": "13/02/2025 12:55"
  },

  {
    "estadio": "Norte",
    "banda": "AUTENTICOS DECADENTES",
    "fecha": "16/02/2025 00:40"
  },
  {
    "estadio": "Norte",
    "banda": "DILLOM",
    "fecha": "15/02/2025 23:10"
  },
  {
    "estadio": "Norte",
    "banda": "AIRBAG",
    "fecha": "15/02/2025 21:40"
  },
  {
    "estadio": "Norte",
    "banda": "Divididos",
    "fecha": "15/02/2025 19:35"
  },
  {
    "estadio": "Norte",
    "banda": "EL MATO A UN POLICIA MOTORIZADO",
    "fecha": "15/02/2025 17:50"
  },
  {
    "estadio": "Norte",
    "banda": "HILDA CANTA A CHARLY",
    "fecha": "15/02/2025 16:30"
  },
  {
    "estadio": "Norte",
    "banda": "KOINO YOKAN",
    "fecha": "15/02/2025 15:20"
  },
  {
    "estadio": "Norte",
    "banda": "SANTI CELLI",
    "fecha": "15/02/2025 14:30"
  },
  {
    "estadio": "Sur",
    "banda": "RATONES PARANOICOS",
    "fecha": "16/02/2025 00:30"
  },
  {
    "estadio": "Sur",
    "banda": "LAS PASTILLAS DEL ABUELO ",
    "fecha": "15/02/2025 23:10"
  },
  {
    "estadio": "Sur",
    "banda": "BABASONICOS",
    "fecha": "15/02/2025 21:40"
  },
  {
    "estadio": "Sur",
    "banda": "WOS",
    "fecha": "15/02/2025 19:40"
  },
  {
    "estadio": "Sur",
    "banda": "GUASONES",
    "fecha": "15/02/2025 17:50"
  },
  {
    "estadio": "Sur",
    "banda": "LOS TIPITOS",
    "fecha": "15/02/2025 16:30"
  },
  {
    "estadio": "Sur",
    "banda": "JÓVENES PORDIOSEROS",
    "fecha": "15/02/2025 15:20"
  },
  {
    "estadio": "Sur",
    "banda": "RYAN",
    "fecha": "15/02/2025 14:30"
  },
  {
    "estadio": "Montaña",
    "banda": "POPOF B2B SPACE 92",
    "fecha": "16/02/2025 02:00"
  },
  {
    "estadio": "Montaña",
    "banda": "JULIAN JEWEIL",
    "fecha": "16/02/2025 01:00"
  },
  {
    "estadio": "Montaña",
    "banda": "MARIANO MELLINO ",
    "fecha": "16/02/2025 00:00"
  },
  {
    "estadio": "Montaña",
    "banda": "CONOCIENDO RUSIA ",
    "fecha": "15/02/2025 22:40"
  },
  {
    "estadio": "Montaña",
    "banda": "NO TE VA A GUSTAR",
    "fecha": "15/02/2025 20:40"
  },
  {
    "estadio": "Montaña",
    "banda": "LA VELA PUERCA",
    "fecha": "15/02/2025 18:40"
  },
  {
    "estadio": "Montaña",
    "banda": "CRUZANDO EL CHARCO",
    "fecha": "15/02/2025 17:10"
  },
  {
    "estadio": "Montaña",
    "banda": "EL ZAR",
    "fecha": "15/02/2025 15:50"
  },
  {
    "estadio": "Montaña",
    "banda": "INAZULINA",
    "fecha": "15/02/2025 15:00"
  },
  {
    "estadio": "Boomerang",
    "banda": "Polenta",
    "fecha": "16/02/2025 00:00"
  },
  {
    "estadio": "Boomerang",
    "banda": "TURF",
    "fecha": "15/02/2025 22:50"
  },
  {
    "estadio": "Boomerang",
    "banda": "EL PLAN DE LA MARIPOSA",
    "fecha": "15/02/2025 21:30"
  },
  {
    "estadio": "Boomerang",
    "banda": "EMMANUEL HORVILLEUR",
    "fecha": "15/02/2025 20:30"
  },
  {
    "estadio": "Boomerang",
    "banda": "INDIOS",
    "fecha": "15/02/2025 19:20"
  },
  {
    "estadio": "Boomerang",
    "banda": "LEO RIZZI",
    "fecha": "15/02/2025 18:20"
  },
  {
    "estadio": "Boomerang",
    "banda": "SIDDHARTHA",
    "fecha": "15/02/2025 17:20"
  },
  {
    "estadio": "Boomerang",
    "banda": "VINOCIO",
    "fecha": "15/02/2025 16:30"
  },
  {
    "estadio": "Boomerang",
    "banda": "FLORIAN",
    "fecha": "15/02/2025 15:40"
  },
  {
    "estadio": "Boomerang",
    "banda": "UMA",
    "fecha": "15/02/2025 14:50"
  },
  {
    "estadio": "Paraguay",
    "banda": "Fiesta Sabor: Villa Diamante- Coneja China",
    "fecha": "15/02/2025 00:30"
  },
  {
    "estadio": "Paraguay",
    "banda": "Sabor Canela",
    "fecha": "15/02/2025 23:10"
  },
  {
    "estadio": "Paraguay",
    "banda": "Los Tabaleros",
    "fecha": "15/02/2025 21:30"
  },
  {
    "estadio": "Paraguay",
    "banda": "Ke Personajes",
    "fecha": "15/02/2025 20:10"
  },
  {
    "estadio": "Paraguay",
    "banda": "La Delio Valdez",
    "fecha": "15/02/2025 19:10"
  },
  {
    "estadio": "Paraguay",
    "banda": "Sara Hebe",
    "fecha": "15/02/2025 18:00"
  },
  {
    "estadio": "Paraguay",
    "banda": "Los Peñaloza",
    "fecha": "15/02/2025 17:00"
  },
  {
    "estadio": "Paraguay",
    "banda": "Luana",
    "fecha": "15/02/2025 16:00"
  },
  {
    "estadio": "Paraguay",
    "banda": "Kamada",
    "fecha": "15/02/2025 15:30"
  },
  {
    "estadio": "La Casita del Blues",
    "banda": "TRIBUTO A PAPPO",
    "fecha": "15/02/2025 22:40"
  },
  {
    "estadio": "La Casita del Blues",
    "banda": "MEMPHIS LA BLUSERA",
    "fecha": "15/02/2025 21:15"
  },
  {
    "estadio": "La Casita del Blues",
    "banda": "CLAUDIA SETTE Y TOYO BAGOSO",
    "fecha": "15/02/2025 20:10"
  },
  {
    "estadio": "La Casita del Blues",
    "banda": "LOS ESPÍRITUS",
    "fecha": "15/02/2025 18:55"
  },
  {
    "estadio": "La Casita del Blues",
    "banda": "CLAUDETTE KING",
    "fecha": "15/02/2025 17:50"
  },
  {
    "estadio": "La Casita del Blues",
    "banda": "YULIE Y VANE RUTH",
    "fecha": "15/02/2025 16:55"
  },
  {
    "estadio": "La Casita del Blues",
    "banda": "THE GINGER HEARTS",
    "fecha": "15/02/2025 16:00"
  },
  {
    "estadio": "La Casita del Blues",
    "banda": "LOS MENTIDORES",
    "fecha": "15/02/2025 15:00"
  },

  {
    "estadio": "Hangar",
    "banda": "DJs PAREJA",
    "fecha": "15/02/2025 22:00"
  },
  {
    "estadio": "Hangar",
    "banda": "LUPE",
    "fecha": "15/02/2025 21:00"
  },
  {
    "estadio": "Hangar",
    "banda": "MABEL",
    "fecha": "15/02/2025 20:00"
  },
  {
    "estadio": "Hangar",
    "banda": "GABA",
    "fecha": "15/02/2025 18:00"
  },
  {
    "estadio": "Hangar",
    "banda": "MARTI DEATH",
    "fecha": "15/02/2025 17:00"
  },
  {
    "estadio": "Norte",
    "banda": "LUCK RA",
    "fecha": "17/02/2025 00:00"
  },
  {
    "estadio": "Norte",
    "banda": "NAFTA",
    "fecha": "16/02/2025 23:00"
  },
  {
    "estadio": "Norte",
    "banda": "LA DELIO VALDEZ",
    "fecha": "16/02/2025 21:00"
  },
  {
    "estadio": "Norte",
    "banda": "NICKI NICOLE",
    "fecha": "16/02/2025 19:40"
  },
  {
    "estadio": "Norte",
    "banda": "CA7RIEL Y PACO AMOROSO",
    "fecha": "16/02/2025 17:50"
  },
  {
    "estadio": "Norte",
    "banda": "BHAVI",
    "fecha": "16/02/2025 16:30"
  },
  {
    "estadio": "Norte",
    "banda": "AGUSFORTNITE2008 & STIFFY",
    "fecha": "16/02/2025 15:20"
  },
  {
    "estadio": "Norte",
    "banda": "K4",
    "fecha": "16/02/2025 14:30"
  },
  {
    "estadio": "Sur",
    "banda": "LOS PIOJOS",
    "fecha": "16/02/2025 22:00"
  },
  {
    "estadio": "Sur",
    "banda": "SKAY Y LOS FAKIRES",
    "fecha": "16/02/2025 20:30"
  },
  {
    "estadio": "Sur",
    "banda": "LAS PELOTAS",
    "fecha": "16/02/2025 19:10"
  },
  {
    "estadio": "Sur",
    "banda": "ALE KURZ",
    "fecha": "16/02/2025 17:50"
  },
  {
    "estadio": "Sur",
    "banda": "LA CHANCHA MUDA",
    "fecha": "16/02/2025 16:30"
  },
  {
    "estadio": "Sur",
    "banda": "WAYRA IGLESIAS",
    "fecha": "16/02/2025 15:20"
  },
  {
    "estadio": "Sur",
    "banda": "DANIELA MILAGROS",
    "fecha": "16/02/2025 14:30"
  },
  {
    "estadio": "Montaña",
    "banda": "PECES RAROS",
    "fecha": "17/02/2025 00:20"
  },
  {
    "estadio": "Montaña",
    "banda": "JUAN HANSEN LIVE",
    "fecha": "16/02/2025 23:10"
  },
  {
    "estadio": "Montaña",
    "banda": "DEADMAU5",
    "fecha": "16/02/2025 20:40"
  },
  {
    "estadio": "Montaña",
    "banda": "BANDALOS CHINOS",
    "fecha": "16/02/2025 18:40"
  },
  {
    "estadio": "Montaña",
    "banda": "SILVESTRE Y LA NARANJA",
    "fecha": "16/02/2025 17:10"
  },
  {
    "estadio": "Montaña",
    "banda": "BLAIR",
    "fecha": "16/02/2025 15:50"
  },
  {
    "estadio": "Montaña",
    "banda": "GENITALLICA",
    "fecha": "16/02/2025 14:30"
  },
  {
    "estadio": "Paraguay",
    "banda": "HIJO DE LA TORMENTA",
    "fecha": "16/02/2025 23:30"
  },
  {
    "estadio": "Paraguay",
    "banda": "ROSA PROFUNDA",
    "fecha": "16/02/2025 22:30"
  },
  {
    "estadio": "Paraguay",
    "banda": "WINONA RIDERS",
    "fecha": "16/02/2025 21:30"
  },
  {
    "estadio": "Paraguay",
    "banda": "MASSACRE",
    "fecha": "16/02/2025 20:10"
  },
  {
    "estadio": "Paraguay",
    "banda": "VAPORS OF MORPHINE",
    "fecha": "16/02/2025 19:00"
  },
  {
    "estadio": "Paraguay",
    "banda": "ZOE GOTUSSO",
    "fecha": "16/02/2025 18:00"
  },
  {
    "estadio": "Paraguay",
    "banda": "JAVIERA MENA",
    "fecha": "16/02/2025 16:50"
  },
  {
    "estadio": "Paraguay",
    "banda": "MANU MARTÍNEZ",
    "fecha": "16/02/2025 16:00"
  },
  {
    "estadio": "Paraguay",
    "banda": "LARA 91K",
    "fecha": "16/02/2025 15:10"
  },
  {
    "estadio": "Paraguay",
    "banda": "FONSO Y LAS PARITARIAS",
    "fecha": "16/02/2025 14:20"
  },
  {
    "estadio": "Paraguay",
    "banda": "Quentin",
    "fecha": "16/02/2025 15:00"
  },
  {
    "estadio": "La Casita del Blues",
    "banda": "LOS BÚFALOS SEDIENTOS",
    "fecha": "16/02/2025 22:45"
  },
  {
    "estadio": "La Casita del Blues",
    "banda": "IVAN SINGH & SHERYL YOUNGBLOOD",
    "fecha": "16/02/2025 21:45"
  },
  {
    "estadio": "La Casita del Blues",
    "banda": "PITI FERNÁNDEZ",
    "fecha": "16/02/2025 20:30"
  },
  {
    "estadio": "La Casita del Blues",
    "banda": "THE RHYTHM GAMBLERS",
    "fecha": "16/02/2025 19:25"
  },
  {
    "estadio": "La Casita del Blues",
    "banda": "CÉSAR VALDOMIR + MARI POLE + NICO RAFFETTA",
    "fecha": "16/02/2025 18:20"
  },
  {
    "estadio": "La Casita del Blues",
    "banda": "SOL BASSA",
    "fecha": "16/02/2025 17:25"
  },
  {
    "estadio": "La Casita del Blues",
    "banda": "CINDY COLEONI",
    "fecha": "16/02/2025 16:20"
  },
  {
    "estadio": "La Casita del Blues",
    "banda": "MARLENE SUCHY & THE SUPER SAX",
    "fecha": "16/02/2025 15:25"
  },
  {
    "estadio": "La Casita del Blues",
    "banda": "PAPI CHIMI ROMERO & BROSSOUL",
    "fecha": "16/02/2025 14:30"
  },
  {
    "estadio": "Hangar",
    "banda": "SOL ORTEGA",
    "fecha": "16/02/2025 21:00"
  },
  {
    "estadio": "Hangar",
    "banda": "PAMPA",
    "fecha": "16/02/2025 20:00"
  },
  {
    "estadio": "Hangar",
    "banda": "J CATRIEL",
    "fecha": "16/02/2025 19:00"
  },
  {
    "estadio": "Hangar",
    "banda": "MAIA DROSS",
    "fecha": "16/02/2025 18:00"
  },
  {
    "estadio": "Hangar",
    "banda": "SIVINSKI",
    "fecha": "16/02/2025 17:00"
  }
]
